hashable_collections/__init__.py
hashable_collections/hashable_collections.py
hashable_collections-1.1.dist-info/METADATA
hashable_collections-1.1.dist-info/top_level.txt
hashable_collections-1.1.dist-info/WHEEL
hashable_collections-1.1.dist-info/DESCRIPTION.rst
hashable_collections-1.1.dist-info/RECORD
hashable_collections-1.1.dist-info/metadata.json
