Metadata-Version: 2.0
Name: hashable-collections
Version: 1.1
Summary: Hashable dictionaries and lists
Home-page: http://akshatm.github.io/hashable_collections/
Author: Akshat Mahajan
Author-email: akshatm.bkk@gmail.com
License: MIT
Keywords: hash,dictionary,lists
Platform: UNKNOWN
Classifier: Intended Audience :: Developers
Classifier: Intended Audience :: Information Technology
Classifier: Intended Audience :: Other Audience
Classifier: Intended Audience :: Science/Research
Classifier: License :: OSI Approved :: MIT License
Classifier: Operating System :: OS Independent
Classifier: Programming Language :: Python
Classifier: Programming Language :: Python :: 2
Classifier: Programming Language :: Python :: 3
Classifier: Programming Language :: Python :: Implementation :: CPython
Classifier: Topic :: Software Development
Classifier: Topic :: Utilities
